omnivoreql/__init__.py
omnivoreql/models.py
omnivoreql/omnivoreql.py
omnivoreql/queries/ApplyLabels.graphql
omnivoreql/queries/ArchiveSavedItem.graphql
omnivoreql/queries/ArticleContent.graphql
omnivoreql/queries/CreateHighlight.graphql
omnivoreql/queries/CreateLabel.graphql
omnivoreql/queries/DeleteHighlight.graphql
omnivoreql/queries/DeleteLabel.graphql
omnivoreql/queries/DeleteSavedItem.graphql
omnivoreql/queries/GetSubscriptions.graphql
omnivoreql/queries/Labels.graphql
omnivoreql/queries/MergeHighlight.graphql
omnivoreql/queries/ReadingProgressMutation.graphql
omnivoreql/queries/SavePage.graphql
omnivoreql/queries/SaveUrl.graphql
omnivoreql/queries/Search.graphql
omnivoreql/queries/TypeAheadSearch.graphql
omnivoreql/queries/UpdateHighlight.graphql
omnivoreql/queries/UpdateLabel.graphql
omnivoreql/queries/UpdatePage.graphql
omnivoreql/queries/UpdatesSince.graphql
omnivoreql/queries/ValidateUsername.graphql
omnivoreql/queries/Viewer.graphql
omnivoreql/queries/schema.graphqls
omnivoreql-0.3.4.dist-info/LICENSE
omnivoreql-0.3.4.dist-info/METADATA
omnivoreql-0.3.4.dist-info/WHEEL
omnivoreql-0.3.4.dist-info/top_level.txt
omnivoreql-0.3.4.dist-info/RECORD
