Metadata-Version: 2.1
Name: omnivoreql
Version: 0.3.4
Summary: Omnivore API Client for Python
Home-page: https://github.com/yazdipour/OmnivoreQL
Author: Shahriar Yazdipour
Author-email: git@yazdipour.com
License: MIT
Project-URL: Bug Tracker, https://github.com/yazdipour/OmnivoreQL/issues
Project-URL: Source Code, https://github.com/yazdipour/OmnivoreQL
Keywords: omnivore api readlater graphql gql client
Platform: any
Classifier: Intended Audience :: Developers
Classifier: Topic :: Software Development :: Libraries
Classifier: Programming Language :: Python :: 3
Classifier: License :: OSI Approved :: MIT License
Requires-Python: >=3
License-File: LICENSE
Requires-Dist: python-dotenv
Requires-Dist: gql >=3.5.0
Requires-Dist: requests-toolbelt >=1.0.0
